rlpy/gym.py
rlpy/__init__.py
rlpy/mdp_solvers/trajectory_based_value_iteration.py
rlpy/mdp_solvers/policy_iteration.py
rlpy/mdp_solvers/trajectory_based_policy_iteration.py
rlpy/mdp_solvers/value_iteration.py
rlpy/mdp_solvers/mdp_solver.py
rlpy/mdp_solvers/__init__.py
rlpy/agents/lspi_sarsa.py
rlpy/agents/lspi.py
rlpy/agents/agent.py
rlpy/agents/natural_actor_critic.py
rlpy/agents/mbie_eb.py
rlpy/agents/psrl.py
rlpy/agents/count_based_bonus.py
rlpy/agents/greedy_gq.py
rlpy/agents/_vi_impl.py
rlpy/agents/batch_agent.py
rlpy/agents/__init__.py
rlpy/agents/td_control_agents.py
rlpy/policies/gibbs.py
rlpy/policies/uniform_random.py
rlpy/policies/e_greedy.py
rlpy/policies/fixed_policies.py
rlpy/policies/policy.py
rlpy/policies/__init__.py
rlpy/policies/swimmer_policy.py
rlpy/experiments/mdpsolver_experiment.py
rlpy/experiments/experiment.py
rlpy/experiments/__init__.py
rlpy/representations/independent_discretization.py
rlpy/representations/kernels.cpp
rlpy/representations/bebf.py
rlpy/representations/representation.py
rlpy/representations/independent_discretization_compact_binary.py
rlpy/representations/kernelized_ifdd.py
rlpy/representations/c_kernels.pxd
rlpy/representations/tabular.py
rlpy/representations/slow_kernels.py
rlpy/representations/hashing.c
rlpy/representations/fourier.py
rlpy/representations/incremental_tabular.py
rlpy/representations/c_kernels.cc
rlpy/representations/omptd.py
rlpy/representations/value_learner.py
rlpy/representations/hashing.cpython-38-x86_64-linux-gnu.so
rlpy/representations/rbf.py
rlpy/representations/tile_coding.py
rlpy/representations/ifdd.py
rlpy/representations/local_bases.py
rlpy/representations/kernels.cpython-38-x86_64-linux-gnu.so
rlpy/representations/__init__.py
rlpy/domains/pst.py
rlpy/domains/cartpole_base.py
rlpy/domains/bicycle.py
rlpy/domains/pinball.py
rlpy/domains/domain.py
rlpy/domains/hiv_treatment_dynamics.c
rlpy/domains/intruder_monitoring.py
rlpy3-2.0.0.dist-info/WHEEL
rlpy3-2.0.0.dist-info/top_level.txt
rlpy3-2.0.0.dist-info/LICENSE.txt
rlpy3-2.0.0.dist-info/RECORD
rlpy3-2.0.0.dist-info/METADATA
