Metadata-Version: 2.1
Name: rlpy3
Version: 2.0.0
Summary: Value-Function-Based Reinforcement-Learning Library for Education and Research: Python3 Fork
Home-page: https://github.com/kngwyu/rlpy
Maintainer: Yuji Kanagawa
Maintainer-email: yuji.kngw.80s.revive@gmail.com
License: BSD 3-clause
Platform: UNKNOWN
Classifier: Intended Audience :: Science/Research
Classifier: Intended Audience :: Developers
Classifier: License :: OSI Approved
Classifier: Programming Language :: C++
Classifier: Programming Language :: Python
Classifier: Topic :: Scientific/Engineering
Classifier: Operating System :: POSIX :: Linux
Classifier: Programming Language :: Python :: 3
Classifier: Programming Language :: Python :: 3.6
Classifier: Programming Language :: Python :: 3.7
Requires-Python: >=3.6.0
Requires-Dist: numpy (>=1.15)
Requires-Dist: scipy (>=1.3)
Requires-Dist: matplotlib (>=3.1)
Requires-Dist: click (>=6.0)
Provides-Extra: bebf
Requires-Dist: scikit-learn ; extra == 'bebf'
Provides-Extra: gym
Requires-Dist: gym (>=0.14.0) ; extra == 'gym'
Provides-Extra: systemadmin
Requires-Dist: networkx ; extra == 'systemadmin'
